pywikihow/__init__.py
pywikihow/exceptions.py
pywikihow/version.py
pywikihow-0.5.6a1.dist-info/LICENSE.md
pywikihow-0.5.6a1.dist-info/METADATA
pywikihow-0.5.6a1.dist-info/WHEEL
pywikihow-0.5.6a1.dist-info/top_level.txt
pywikihow-0.5.6a1.dist-info/RECORD
