Metadata-Version: 2.1
Name: pywikihow
Version: 0.5.6a1
Summary: unofficial wikihow python api
Home-page: https://github.com/OpenJarbas/PyWikiHow
Author: jarbasai
Author-email: jarbasai@mailfence.com
License: MIT
Platform: UNKNOWN
Requires-Dist: requests
Requires-Dist: bs4
Requires-Dist: requests-cache
